cg_singer
