Metadata-Version: 2.1
Name: cg-singer
Version: 0.0.2
Summary: A small example package
Home-page: https://github.com/csinger77/code_golf
Author: Chistopher Singer
Author-email: christopher.singer.analytics@gmail.com
License: UNKNOWN
Platform: UNKNOWN
Classifier: Programming Language :: Python :: 3
Classifier: License :: OSI Approved :: MIT License
Classifier: Operating System :: OS Independent
Requires-Python: >=3.6
